mdx_emdash.py
markdown_emdash-0.2.0.dist-info/LICENSE
markdown_emdash-0.2.0.dist-info/METADATA
markdown_emdash-0.2.0.dist-info/WHEEL
markdown_emdash-0.2.0.dist-info/top_level.txt
markdown_emdash-0.2.0.dist-info/RECORD
