Metadata-Version: 2.1
Name: markdown-emdash
Version: 0.2.0
Summary: Extension for python-markdown that replaces all triple dashes em-dashes.
Home-page: https://github.com/czue/markdown-emdash
Author: Cory Zue
Author-email: cory@coryzue.com
License: MIT License
Classifier: Environment :: Web Environment
Classifier: Intended Audience :: Developers
Classifier: License :: OSI Approved :: MIT License
Classifier: Operating System :: OS Independent
Classifier: Programming Language :: Python
Classifier: Programming Language :: Python :: 3.8
Classifier: Programming Language :: Python :: 3.9
Classifier: Programming Language :: Python :: 3.10
Classifier: Programming Language :: Python :: 3.11
Classifier: Topic :: Internet :: WWW/HTTP
Classifier: Topic :: Internet :: WWW/HTTP :: Dynamic Content
License-File: LICENSE
